{
  "compatibility-mode" : false,
  "constants": {
    "@main-font": [ "noto-mix", "noto-cjk" ],
    "@devil": [ "smiley", 54, 49, 30, 30 ],
    "@sleepy": [ "smiley", 154, 94, 30, 30 ]
  },
  "fonts": {
    "noto-mix": "//cdn.melown.com/libs/vtsjs/fonts/noto-extended/1.0.0/noto.fnt",
    "noto-cjk": "//cdn.melown.com/libs/vtsjs/fonts/noto-cjk/1.0.0/noto.fnt",
    "#default": "//cdn.melown.com/libs/vtsjs/fonts/noto-basic/1.0.0/noto.fnt"
  },
  "bitmaps": {
    "smiley": "smiley.jpeg"
  },
  "layers": {
    "lines-flat-ratio": {
      "filter": [
        "all",
        [ "==", "#group", "transportation" ],
        [
          "==",
          {
            "mod": [
              { "strhash": "#id" },
              4
            ]
          },
          0
        ]
      ],
      "line": true,
      "line-flat": true,
      "line-width": 0.01,
      "line-width-units": "ratio",
      "line-color": [ 255, 0, 0, 120 ],
      "zbuffer-offset": [ -0.2, 0, 0 ],
      "z-index": 1,
      "culling": 89
    },
    "lines-screen-ratio": {
      "filter": [
        "all",
        [ "==", "#group", "transportation" ],
        [
          "==",
          {
            "mod": [
              { "strhash": "#id" },
              4
            ]
          },
          1
        ]
      ],
      "line": true,
      "line-flat": false,
      "line-width": 0.01,
      "line-width-units": "ratio",
      "line-color": [ 0, 0, 255, 120 ],
      "zbuffer-offset": [ -0.2, 0, 0 ],
      "z-index": 2,
      "culling": 89
    },
    "lines-flat": {
      "filter": [
        "all",
        [ "==", "#group", "transportation" ],
        [
          "==",
          {
            "mod": [
              { "strhash": "#id" },
              4
            ]
          },
          2
        ]
      ],
      "line": true,
      "line-flat": true,
      "line-width": 200,
      "line-color": [ 255, 255, 0, 120 ],
      "zbuffer-offset": [ -0.2, 0, 0 ],
      "z-index": 3,
      "culling": 89
    },
    "lines-screen": {
      "filter": [
        "all",
        [ "==", "#group", "transportation" ],
        [
          "==",
          {
            "mod": [
              { "strhash": "#id" },
              4
            ]
          },
          3
        ]
      ],
      "line": true,
      "line-flat": false,
      "line-width": 10,
      "line-color": [ 0, 255, 255, 120 ],
      "zbuffer-offset": [ -0.2, 0, 0 ],
      "z-index": 4,
      "culling": 89
    },
    "icons-flat-ratio": {
      "filter": [
        "all",
        [ "==", "#group", "place" ],
        [ "==", "$class", "town" ],
        [
          "==",
          {
            "mod": [
              { "strhash": "#id" },
              4
            ]
          },
          0
        ]
      ],
      "point": true,
      "point-flat": true,
      "point-radius": 0.02,
      "point-radius-units": "ratio",
      "point-color": [ 255, 0, 0, 120 ],
      "zbuffer-offset": [ -0.2, 0, 0 ],
      "z-index": 5,
      "culling": 89
    },
    "icons-screen-ratio": {
      "filter": [
        "all",
        [ "==", "#group", "place" ],
        [ "==", "$class", "town" ],
        [
          "==",
          {
            "mod": [
              { "strhash": "#id" },
              4
            ]
          },
          1
        ]
      ],
      "point": true,
      "point-flat": false,
      "point-radius": 0.02,
      "point-radius-units": "ratio",
      "point-color": [ 0, 0, 255, 120 ],
      "zbuffer-offset": [ -0.2, 0, 0 ],
      "z-index": 6,
      "culling": 89
    },
    "icons-flat": {
      "filter": [
        "all",
        [ "==", "#group", "place" ],
        [ "==", "$class", "town" ],
        [
          "==",
          {
            "mod": [
              { "strhash": "#id" },
              4
            ]
          },
          2
        ]
      ],
      "point": true,
      "point-flat": true,
      "point-radius": 500,
      "point-color": [ 255, 255, 0, 120 ],
      "zbuffer-offset": [ -0.2, 0, 0 ],
      "z-index": 7,
      "culling": 89
    },
    "icons-screen": {
      "filter": [
        "all",
        [ "==", "#group", "place" ],
        [ "==", "$class", "town" ],
        [
          "==",
          {
            "mod": [
              { "strhash": "#id" },
              4
            ]
          },
          3
        ]
      ],
      "point": true,
      "point-flat": false,
      "point-radius": 10,
      "point-color": [ 0, 255, 255, 120 ],
      "zbuffer-offset": [ -0.2, 0, 0 ],
      "z-index": 8,
      "culling": 89
    }
  }
}
